b_elasticsearch_layer/__init__.py
b_elasticsearch_layer/layer.py
b_elasticsearch_layer/source/__init__.py
b_elasticsearch_layer/source/requirements.txt
b_elasticsearch_layer_test/__init__.py
b_elasticsearch_layer_test/testing_app.py
b_elasticsearch_layer_test/testing_infrastructure.py
b_elasticsearch_layer-0.0.6.dist-info/LICENSE
b_elasticsearch_layer-0.0.6.dist-info/METADATA
b_elasticsearch_layer-0.0.6.dist-info/WHEEL
b_elasticsearch_layer-0.0.6.dist-info/top_level.txt
b_elasticsearch_layer-0.0.6.dist-info/RECORD
