Metadata-Version: 2.1
Name: b-elasticsearch-layer
Version: 0.0.6
Summary: AWS CDK based lambda layer including Elasticsearch client.
Home-page: https://github.com/biomapas/B.ElasticsearchLayer.git
Author: Laimonas Sutkus
Author-email: laimonas.sutkus@biomapas.com
License: Apache License 2.0
Keywords: AWS CDK Lambda Layer Elasticsearch
Platform: UNKNOWN
Classifier: Programming Language :: Python :: 3
Classifier: Operating System :: OS Independent
Requires-Dist: aws-cdk.core (<2.0.0,>=1.75.0)
Requires-Dist: aws-cdk.aws-lambda (<2.0.0,>=1.75.0)
